setup.py
distributionsbvh/Binomialdistribution.py
distributionsbvh/Gaussiandistribution.py
distributionsbvh/Generaldistribution.py
distributionsbvh/__init__.py
distributionsbvh.egg-info/PKG-INFO
distributionsbvh.egg-info/SOURCES.txt
distributionsbvh.egg-info/dependency_links.txt
distributionsbvh.egg-info/not-zip-safe
distributionsbvh.egg-info/top_level.txt